<?xml version="1.0" encoding="utf-8"?>
<vector xmlns:android="http://schemas.android.com/apk/res/android" android:width="177dp"
    android:height="337dp" android:viewportHeight="337" android:viewportWidth="177">
    <group android:translateX="-208.0126" android:translateY="8.041534">
        <group android:translateX="-52.24044" android:translateY="-455.0495">
            <path android:fillColor="#fec148"
                android:pathData="M287.023 533.258c0 0 -7 -28.5 -4.75 -39.25 -4 6.75 -4 6.75 -4 6.75 0 0 2.5 -23.75 18.5 -31.5 0 0 -5 -0.5 -7 0.75 0 0 13 -22.75 56.75 -17 0 0 27.5 -5.75 42.25 4.75 11.987 8.533 18.5 16.75 20.75 25.5l-3.75 -3.25c0 0 8 9.25 5.5 24.25 -2.5 15 -5.75 21.5 -5.75 21.5l-2.5 7.25c0 0 -1.75 -10 -2 -11 -0.25 -1 -7.25 -23.75 -11.25 -29.5l1 6.25c0 0 -2.25 -9.75 -7.75 -15.25l0 3.5c0 0 -4.75 -9 -14.5 -13.25 0 0 -14.5 2 -28.25 8 -13.75 6 -33.5 12.5 -39.5 25.25 0 0 2.25 -10.75 5.5 -14.25 0 0 -18 16.75 -19.25 40.5z" />
            <path android:fillColor="#000000"
                android:pathData="M368.523 473.758c0 0 -57.5 14.75 -66.25 31.25 0 0 3 -9.25 19 -16.5 16 -7.25 37.5 -14.25 47.25 -14.75z" />
            <path android:fillColor="#000000"
                android:pathData="M405.773 480.008c0 0 7 5.5 5.75 20 -1.25 14.5 -7 28.75 -7 28.75 0 0 6.25 -21.25 6.25 -30.25 0 -9 -5 -18.5 -5 -18.5z" />
            <path android:fillColor="#000000"
                android:pathData="M347.773 453.008c0 0 21.75 -5.25 37.5 2.75 15.75 8 24 22 24.25 27.5 -2.75 -5.5 -14.75 -36.25 -61.75 -30.25z" />
            <path android:fillColor="#000000"
                android:pathData="M368.023 472.508c0 0 12.25 8.75 15 14.5 -0.75 -4.5 -8.25 -12 -15 -14.5z" />
            <path android:fillColor="#000000"
                android:pathData="M383.023 483.508c0 0 6.75 8 7.75 15.25 -1 -9.25 -7.75 -15.25 -7.75 -15.25z" />
            <path android:fillColor="#000000"
                android:pathData="M391.273 494.508c0 0 11 28.25 11.75 38.5 -1.25 -11.25 -5.25 -24.75 -11.75 -38.5z" />
            <path android:fillColor="#000000"
                android:pathData="M287.023 533.258c0 0 2.25 -22.5 19.25 -40.5 -16.75 17 -19.25 31 -19.25 40.5z" />
            <path android:fillColor="#000000"
                android:pathData="M284.273 490.508c0 0 -5.25 6.25 2 37.75 -6.25 -20 -6.75 -32 -2 -37.75z" />
            <path android:fillColor="#000000"
                android:pathData="M278.273 500.758c0 0 5.5 -25.5 18.5 -31.5 -12.25 4.5 -17.75 19.5 -18.5 31.5z" />
            <path android:fillColor="#000000"
                android:pathData="M290.773 468.508c0 0 18.25 -20.25 55.75 -15.5 -8 -4.75 -41.75 -2.75 -55.75 15.5z" />
        </group>
        <group android:translateX="-43.21907" android:translateY="-107.3025">
            <path android:fillColor="#ffe993"
                android:pathData="M304.729 139.503c0 0 29.75 -16 52.25 -16.25 0 0 -37.75 0.25 -52.25 16.25z" />
            <path android:fillColor="#ffe993"
                android:pathData="M298.479 139.253c0 0 14.5 -16 40.75 -16.75 0 0 -32.5 0 -40.75 16.75z" />
            <path android:fillColor="#ffe993"
                android:pathData="M291.229 145.753c0 0 3.25 -16.75 28 -23 0 0 -21.25 6.5 -28 23z" />
            <path android:fillColor="#ffe993"
                android:pathData="M367.979 122.753c0 0 19.75 5.75 23.5 31.25 0 0 -5.75 -22.5 -23.5 -31.25z" />
            <path android:fillColor="#ffe993"
                android:pathData="M366.979 118.503c0 0 24 3.25 27 30.5 0 0 -2.5 -21.75 -27 -30.5z" />
        </group>
    </group>
</vector>